[
  {
    "timestamp": "2020-02-24 08:00:00",
    "date": "2020-02-24",
    "hour": 8,
    "label": "Normal",
    "confidence": 1.0,
    "reason": "All sensor readings within normal range."
  },
  {
    "timestamp": "2020-02-24 09:00:00",
    "date": "2020-02-24",
    "hour": 9,
    "label": "Normal",
    "confidence": 1.0,
    "reason": "All sensor readings within normal range."
  },
  {
    "timestamp": "2020-02-24 10:00:00",
    "date": "2020-02-24",
    "hour": 10,
    "label": "Normal",
    "confidence": 1.0,
    "reason": "All sensor readings within normal range."
  },
  {
    "timestamp": "2020-02-24 11:00:00",
    "date": "2020-02-24",
    "hour": 11,
    "label": "Normal",
    "confidence": 1.0,
    "reason": "All sensor readings within normal range."
  },
  {
    "timestamp": "2020-02-24 12:00:00",
    "date": "2020-02-24",
    "hour": 12,
    "label": "Normal",
    "confidence": 1.0,
    "reason": "All sensor readings within normal range."
  },
  {
    "timestamp": "2020-02-24 13:00:00",
    "date": "2020-02-24",
    "hour": 13,
    "label": "Normal",
    "confidence": 1.0,
    "reason": "All sensor readings within normal range."
  },
  {
    "timestamp": "2020-02-24 14:00:00",
    "date": "2020-02-24",
    "hour": 14,
    "label": "Normal",
    "confidence": 1.0,
    "reason": "All sensor readings within normal range."
  },
  {
    "timestamp": "2020-02-24 15:00:00",
    "date": "2020-02-24",
    "hour": 15,
    "label": "Normal",
    "confidence": 1.0,
    "reason": "All sensor readings within normal range."
  },
  {
    "timestamp": "2020-02-24 16:00:00",
    "date": "2020-02-24",
    "hour": 16,
    "label": "Normal",
    "confidence": 1.0,
    "reason": "All sensor readings within normal range."
  },
  {
    "timestamp": "2020-02-24 17:00:00",
    "date": "2020-02-24",
    "hour": 17,
    "label": "Normal",
    "confidence": 1.0,
    "reason": "All sensor readings within normal range."
  }
]